agents_upstream/__init__.py
agents_upstream/cli.py
agents_upstream/templates/README.md
agents_upstream/templates/.cursor/rules/agent-workflow-orchestrator.mdc
agents_upstream/templates/.cursor/rules/guardrail-validator.md
agents_upstream/templates/.cursor/rules/problem-space/README.md
agents_upstream/templates/.cursor/rules/problem-space/agent-0-product-service-specialist.mdc
agents_upstream/templates/.cursor/rules/problem-space/agent-1-qualitative-research-specialist.mdc
agents_upstream/templates/.cursor/rules/problem-space/agent-2-painpoint-analysis-specialist.mdc
agents_upstream/templates/.cursor/rules/problem-space/agent-3-asis-journey-mapper.mdc
agents_upstream/templates/.cursor/rules/problem-space/agent-4-journey-consolidation-specialist.mdc
agents_upstream/templates/.cursor/rules/problem-space/agent-5-strategic-report-generator.mdc
agents_upstream/templates/.cursor/rules/solution-space/README.md
agents_upstream/templates/.cursor/rules/solution-space/agent-6-strategic-analysis-specialist.mdc
agents_upstream/templates/.cursor/rules/solution-space/agent-7-process-optimization-specialist.mdc
agents_upstream/templates/.cursor/rules/solution-space/agent-8-communication-specialist.mdc
agents_upstream/templates/0-documentation/0a-projectdocs/context.md
agents_upstream/templates/_output-structure/workflow-rules.md
agents_upstream/templates/_output-structure/problem-space/interview-analysis-template.md
agents_upstream/templates/_output-structure/problem-space/journey-mapping-template.md
agents_upstream/templates/_output-structure/problem-space/model-structure.md
agents_upstream/templates/_output-structure/problem-space/pain-point-analysis-template.md
agents_upstream/templates/_output-structure/problem-space/report-template.md
agents_upstream/templates/_output-structure/solution-space/GUARDRAILS-ENFORCEMENT.md
agents_upstream/templates/_output-structure/solution-space/automation-assessment-template.md
agents_upstream-1.4.0.dist-info/licenses/LICENSE
agents_upstream-1.4.0.dist-info/METADATA
agents_upstream-1.4.0.dist-info/WHEEL
agents_upstream-1.4.0.dist-info/entry_points.txt
agents_upstream-1.4.0.dist-info/top_level.txt
agents_upstream-1.4.0.dist-info/RECORD
