Metadata-Version: 2.4
Name: agents-upstream
Version: 1.4.0
Summary: AI-powered research analysis system for product discovery
Home-page: https://github.com/marcelusfernandes/agents-upstream
Author: Agents Upstream Contributors
License: MIT
Project-URL: Homepage, https://github.com/marcelusfernandes/agents-upstream
Project-URL: Repository, https://github.com/marcelusfernandes/agents-upstream
Project-URL: Issues, https://github.com/marcelusfernandes/agents-upstream/issues
Keywords: ai,agents,product-discovery,research-analysis,workflow,cursor-ai
Classifier: Development Status :: 4 - Beta
Classifier: Intended Audience :: Developers
Classifier: License :: OSI Approved :: MIT License
Classifier: Programming Language :: Python :: 3
Classifier: Programming Language :: Python :: 3.8
Classifier: Programming Language :: Python :: 3.9
Classifier: Programming Language :: Python :: 3.10
Classifier: Programming Language :: Python :: 3.11
Classifier: Programming Language :: Python :: 3.12
Classifier: Topic :: Software Development :: Libraries :: Python Modules
Classifier: Topic :: Scientific/Engineering :: Artificial Intelligence
Requires-Python: >=3.8
License-File: LICENSE
Dynamic: home-page
Dynamic: license-file
Dynamic: requires-python
